reclaim_mcp/__init__.py
reclaim_mcp/cache.py
reclaim_mcp/client.py
reclaim_mcp/config.py
reclaim_mcp/exceptions.py
reclaim_mcp/models.py
reclaim_mcp/profiles.py
reclaim_mcp/server.py
reclaim_mcp/tools/__init__.py
reclaim_mcp/tools/analytics.py
reclaim_mcp/tools/events.py
reclaim_mcp/tools/focus.py
reclaim_mcp/tools/habits.py
reclaim_mcp/tools/tasks.py
reclaim_mcp/utils.py
reclaim_mcp_server-0.9.1.dist-info/METADATA
reclaim_mcp_server-0.9.1.dist-info/WHEEL
reclaim_mcp_server-0.9.1.dist-info/entry_points.txt
reclaim_mcp_server-0.9.1.dist-info/licenses/LICENSE
reclaim_mcp_server-0.9.1.dist-info/RECORD
