Metadata-Version: 2.4
Name: reclaim-mcp-server
Version: 0.9.1
Summary: Unofficial MCP server for Reclaim.ai calendar integration
License: MIT
License-File: LICENSE
Keywords: mcp,reclaim,calendar,ai,fastmcp,llm,claude
Author: Falko Sieverding
Requires-Python: >=3.12
Classifier: Development Status :: 4 - Beta
Classifier: Intended Audience :: Developers
Classifier: License :: OSI Approved :: MIT License
Classifier: Programming Language :: Python :: 3
Classifier: Programming Language :: Python :: 3.12
Classifier: Programming Language :: Python :: 3.13
Requires-Dist: fastmcp (>=2.0.0)
Requires-Dist: httpx (>=0.28.0)
Requires-Dist: pydantic (>=2.0.0)
Requires-Dist: pydantic-settings (>=2.0.0)
Project-URL: Bug Tracker, https://gitlab.com/universalamateur1/reclaim-mcp-server/-/issues
Project-URL: Changelog, https://gitlab.com/universalamateur1/reclaim-mcp-server/-/blob/main/CHANGELOG.md
Project-URL: Documentation, https://gitlab.com/universalamateur1/reclaim-mcp-server/-/blob/main/docs/API.md
Project-URL: Homepage, https://gitlab.com/universalamateur1/reclaim-mcp-server
Project-URL: Repository, https://gitlab.com/universalamateur1/reclaim-mcp-server
